setup.py
dm/__init__.py
dm.zdoc.egg-info/PKG-INFO
dm.zdoc.egg-info/SOURCES.txt
dm.zdoc.egg-info/dependency_links.txt
dm.zdoc.egg-info/entry_points.txt
dm.zdoc.egg-info/namespace_packages.txt
dm.zdoc.egg-info/requires.txt
dm.zdoc.egg-info/top_level.txt
dm.zdoc.egg-info/zip-safe
dm/zdoc/LICENSE.txt
dm/zdoc/README.txt
dm/zdoc/VERSION.txt
dm/zdoc/__init__.py
dm/zdoc/browser.py
dm/zdoc/configure.zcml