Metadata-Version: 1.0
Name: dm.zdoc
Version: 2.0
Summary: pydoc based documentation for Zope
Home-page: UNKNOWN
Author: Dieter Maurer
Author-email: dieter@handshake.de
License: BSD (see "dm/zdoc/LICENSE.txt", for details)
Keywords: pydoc documentation Zope
Platform: UNKNOWN
Classifier: Development Status :: 5 - Production/Stable
Classifier: Framework :: Zope2
Classifier: Intended Audience :: Developers
Classifier: License :: OSI Approved :: BSD License
Classifier: Operating System :: OS Independent
Classifier: Programming Language :: Python
Classifier: Topic :: Documentation
